xtrapnet/__init__.py
xtrapnet/config.py
xtrapnet/controller.py
xtrapnet/model.py
xtrapnet/pipeline.py
xtrapnet/trainer.py
xtrapnet/adaptive/__init__.py
xtrapnet/adaptive/active_learning.py
xtrapnet/adaptive/continual_learning.py
xtrapnet/adaptive/memory_bank.py
xtrapnet/adaptive/meta_learner.py
xtrapnet/adaptive/online_adaptation.py
xtrapnet/anomaly/__init__.py
xtrapnet/anomaly/anomaly_benchmark.py
xtrapnet/anomaly/deployment_tools.py
xtrapnet/anomaly/explainable_anomaly.py
xtrapnet/anomaly/multi_modal_detector.py
xtrapnet/anomaly/real_time_monitor.py
xtrapnet/bayesian/__init__.py
xtrapnet/bayesian/bnn.py
xtrapnet/bayesian/conformal.py
xtrapnet/bayesian/mcmc.py
xtrapnet/bayesian/uncertainty.py
xtrapnet/bayesian/variational.py
xtrapnet/benchmarks/__init__.py
xtrapnet/benchmarks/benchmark_datasets.py
xtrapnet/benchmarks/benchmark_suite.py
xtrapnet/benchmarks/evaluation_metrics.py
xtrapnet/benchmarks/fever_dataset.py
xtrapnet/benchmarks/reporting.py
xtrapnet/core/__init__.py
xtrapnet/core/adaptive_uncertainty.py
xtrapnet/core/extrapolation_meta_learning.py
xtrapnet/core/physics_constrained.py
xtrapnet/core/sota_benchmark.py
xtrapnet/llm/__init__.py
xtrapnet/llm/decision_maker.py
xtrapnet/llm/fever_classifier.py
xtrapnet/llm/llm_assistant.py
xtrapnet/llm/ood_explainer.py
xtrapnet/physics/__init__.py
xtrapnet/physics/domain_aware.py
xtrapnet/physics/physics_loss.py
xtrapnet/physics/pinn.py
xtrapnet-1.0.0.dist-info/METADATA
xtrapnet-1.0.0.dist-info/WHEEL
xtrapnet-1.0.0.dist-info/top_level.txt
xtrapnet-1.0.0.dist-info/RECORD
