Metadata-Version: 2.4
Name: xtrapnet
Version: 1.0.0
Summary: Novel framework for extrapolation control with Adaptive Uncertainty Decomposition, Constraint Satisfaction Networks, and Extrapolation-Aware Meta-Learning
Home-page: https://github.com/cykurd/xtrapnet
Author: cykurd
Author-email: cykurd@gmail.com
Classifier: Programming Language :: Python :: 3
Classifier: License :: OSI Approved :: MIT License
Classifier: Operating System :: OS Independent
Requires-Python: >=3.8
Requires-Dist: torch>=2.0.0
Requires-Dist: numpy>=1.21.0
Requires-Dist: scipy>=1.7.0
Requires-Dist: scikit-learn>=1.0.0
Requires-Dist: matplotlib>=3.5.0
Requires-Dist: transformers>=4.20.0
Requires-Dist: datasets>=2.0.0
Requires-Dist: flask>=2.0.0
Requires-Dist: pyyaml>=6.0
Requires-Dist: psutil>=5.8.0
Dynamic: author
Dynamic: author-email
Dynamic: classifier
Dynamic: description
Dynamic: description-content-type
Dynamic: home-page
Dynamic: requires-dist
Dynamic: requires-python
Dynamic: summary
